Workbook

Sheet Dashboard
A1: EchoForge Creative Network Dashboard — May 2026
A2: Where Ideas Take Shape.
A3: Owner: Darren Ethier | Platform: EchoForge | Services: Audio Editing · Graphic Design · AI Prompting · 3D Rendering · Video Production · Content Writing
A5: Total Projects | E5: Active Creators | I5: Delivery Rate | M5: Monthly MRR
A6: =COUNTA('Client Projects'!A2:A1000) | E6: =COUNTIF(Creators!E2:E1000,"Available") | I6: =IFERROR(COUNTIF('Client Projects'!M2:M1000,"Completed")/COUNTA('Client Projects'!A2:A1000),0) | M6: =IFERROR(SUM('Revenue & Invoices'!G2:G13)/COUNTA('Revenue & Invoices'!A2:A13),0)
A7: from Client Projects | E7: Availability = Available | I7: % status = Completed | M7: avg monthly revenue
A9: Projects by Service Type | I9: Monthly Revenue Trend (2026)
A10: Service Type | B10: Project Count | I10: Month | J10: Std Rev | K10: Boost Rev | L10: Rush Sur | M10: Total Rev | N10: Cumul Rev
A11: Audio Editing | B11: =COUNTIF('Client Projects'!F:F,"Audio Editing") | I11: Jan | J11: ='Revenue & Invoices'!C2 | K11: ='Revenue & Invoices'!E2 | L11: ='Revenue & Invoices'!F2 | M11: ='Revenue & Invoices'!G2 | N11: ='Revenue & Invoices'!H2
A12: Graphic Design | B12: =COUNTIF('Client Projects'!F:F,"Graphic Design") | I12: Feb | J12: ='Revenue & Invoices'!C3 | K12: ='Revenue & Invoices'!E3 | L12: ='Revenue & Invoices'!F3 | M12: ='Revenue & Invoices'!G3 | N12: ='Revenue & Invoices'!H3
A13: AI Prompting | B13: =COUNTIF('Client Projects'!F:F,"AI Prompting") | I13: Mar | J13: ='Revenue & Invoices'!C4 | K13: ='Revenue & Invoices'!E4 | L13: ='Revenue & Invoices'!F4 | M13: ='Revenue & Invoices'!G4 | N13: ='Revenue & Invoices'!H4
A14: 3D Rendering | B14: =COUNTIF('Client Projects'!F:F,"3D Rendering") | I14: Apr | J14: ='Revenue & Invoices'!C5 | K14: ='Revenue & Invoices'!E5 | L14: ='Revenue & Invoices'!F5 | M14: ='Revenue & Invoices'!G5 | N14: ='Revenue & Invoices'!H5
A15: Video Production | B15: =COUNTIF('Client Projects'!F:F,"Video Production") | I15: May | J15: ='Revenue & Invoices'!C6 | K15: ='Revenue & Invoices'!E6 | L15: ='Revenue & Invoices'!F6 | M15: ='Revenue & Invoices'!G6 | N15: ='Revenue & Invoices'!H6
A16: Content Writing | B16: =COUNTIF('Client Projects'!F:F,"Content Writing") | I16: Jun | J16: ='Revenue & Invoices'!C7 | K16: ='Revenue & Invoices'!E7 | L16: ='Revenue & Invoices'!F7 | M16: ='Revenue & Invoices'!G7 | N16: ='Revenue & Invoices'!H7
I17: Jul | J17: ='Revenue & Invoices'!C8 | K17: ='Revenue & Invoices'!E8 | L17: ='Revenue & Invoices'!F8 | M17: ='Revenue & Invoices'!G8 | N17: ='Revenue & Invoices'!H8
I18: Aug | J18: ='Revenue & Invoices'!C9 | K18: ='Revenue & Invoices'!E9 | L18: ='Revenue & Invoices'!F9 | M18: ='Revenue & Invoices'!G9 | N18: ='Revenue & Invoices'!H9
I19: Sep | J19: ='Revenue & Invoices'!C10 | K19: ='Revenue & Invoices'!E10 | L19: ='Revenue & Invoices'!F10 | M19: ='Revenue & Invoices'!G10 | N19: ='Revenue & Invoices'!H10
I20: Oct | J20: ='Revenue & Invoices'!C11 | K20: ='Revenue & Invoices'!E11 | L20: ='Revenue & Invoices'!F11 | M20: ='Revenue & Invoices'!G11 | N20: ='Revenue & Invoices'!H11
I21: Nov | J21: ='Revenue & Invoices'!C12 | K21: ='Revenue & Invoices'!E12 | L21: ='Revenue & Invoices'!F12 | M21: ='Revenue & Invoices'!G12 | N21: ='Revenue & Invoices'!H12
I22: Dec | J22: ='Revenue & Invoices'!C13 | K22: ='Revenue & Invoices'!E13 | L22: ='Revenue & Invoices'!F13 | M22: ='Revenue & Invoices'!G13 | N22: ='Revenue & Invoices'!H13
A42: EchoForge Creative Network | Owner: Darren Ethier | Barrie, ON, Canada | Updated: May 23, 2026

Sheet Client Projects
A1: EchoForge — Client Projects
A2: ID | B2: Date | C2: Client Name | D2: Email | E2: Phone | F2: Service Type | G2: Project Title | H2: Description | I2: Deadline | J2: Budget ($) | K2: Rush | L2: Status | M2: Assigned Creator | N2: Delivery Date | O2: Notes | P2: Project Score
A3: PRJ-001 | B3: 46032 | C3: Mira Connelly | D3: mira.connelly@gmail.com | E3: 705-555-0192 | F3: Audio Editing | G3: Podcast Series Cut #1 | H3: Edit 5-episode podcast, noise reduction & mastering | I3: 46050 | J3: 350 | K3: No | L3: Completed | M3: Jordan Park | N3: 46048 | O3: Client very satisfied | P3: =IF(AND(K3="Yes",J3>500),95,IF(K3="Yes",80,IF(J3>1000,75,50)))
A4: PRJ-002 | B4: 46056 | C4: Theo Bassett | D4: theo.bassett@outlook.com | E4: 705-555-0387 | F4: Graphic Design | G4: Brand Identity Package | H4: Logo, colour palette, business card design | I4: 46073 | J4: 1200 | K4: No | L4: Delivered | M4: Sarai Okon | N4: 46071 | O4: One revision requested | P4: =IF(AND(K4="Yes",J4>500),95,IF(K4="Yes",80,IF(J4>1000,75,50)))
A5: PRJ-003 | B5: 46096 | C5: Luz Ferreira | D5: luz.ferreira@yahoo.com | E5: 647-555-0841 | F5: Video Production | G5: Product Launch Reel | H5: 90-sec launch video with motion graphics, VO | I5: 46113 | J5: 2500 | K5: Yes | L5: In Progress | M5: Cam Whitfield | O5: Rush approved, tight deadline | P5: =IF(AND(K5="Yes",J5>500),95,IF(K5="Yes",80,IF(J5>1000,75,50)))
A6: PRJ-004 | B6: 46134 | C6: Noel Harding | D6: noel.harding@proton.me | E6: 416-555-0034 | F6: AI Prompting | G6: E-commerce Image Prompts | H6: 50 optimised Midjourney prompts for product shots | I6: 46147 | J6: 150 | K6: No | L6: New | O6: Awaiting creator match | P6: =IF(AND(K6="Yes",J6>500),95,IF(K6="Yes",80,IF(J6>1000,75,50)))
A7: PRJ-005 | B7: 46143 | C7: Avery Sloane | D7: avery.sloane@gmail.com | E7: 905-555-0276 | F7: Content Writing | G7: SaaS Blog — 4 Articles | H7: 4 x 1200-word SEO blog posts on productivity tools | I7: 46164 | J7: 680 | K7: Yes | L7: Matched | M7: Dana Voss | O7: Rush surcharge applied | P7: =IF(AND(K7="Yes",J7>500),95,IF(K7="Yes",80,IF(J7>1000,75,50)))

Sheet Creators
A1: EchoForge — Creators / Freelancers
A2: ID | B2: Name | C2: Skills | D2: Portfolio URL | E2: Hourly Rate ($) | F2: Availability | G2: Rating (1-5) | H2: Tier | I2: Turnaround Days | J2: Notes
A3: CRE-001 | B3: Jordan Park | C3: Audio Editing, Podcast Mastering, Noise Reduction | D3: jordanpark.audio | E3: 55 | F3: Available | G3: 4.8 | H3: Forge Boost $79 | I3: 3 | J3: Top-rated audio specialist, Barrie ON
A4: CRE-002 | B4: Sarai Okon | C4: Graphic Design, Branding, Illustration, Typography | D4: saraiokon.design | E4: 70 | F4: Available | G4: 4.9 | H4: Forge Boost $79 | I4: 4 | J4: Brand identity expert, fast turnaround
A5: CRE-003 | B5: Cam Whitfield | C5: Video Production, Motion Graphics, Colour Grading | D5: camwhitfield.video | E5: 95 | F5: Busy | G5: 4.7 | H5: Forge Boost $79 | I5: 5 | J5: Currently on PRJ-003, available June
A6: CRE-004 | B6: Dana Voss | C6: Content Writing, SEO, Copywriting, Blog Posts | D6: danavoss.write | E6: 45 | F6: Available | G6: 4.5 | H6: Standard Free | I6: 3 | J6: Strong SaaS and tech niche experience
A7: CRE-005 | B7: Ren Takahashi | C7: AI Prompting, Midjourney, DALL-E, Stable Diffusion | D7: rentakahashi.ai | E7: 40 | F7: Available | G7: 4.6 | H7: Standard Free | I7: 2 | J7: Specialises in product & e-commerce prompts
A8: CRE-006 | B8: Mika Delacroix | C8: 3D Rendering, Blender, ArchViz, Product Visualisation | D8: mikadelacroix.3d | E8: 85 | F8: On Hold | G8: 4.4 | H8: Forge Boost $79 | I8: 6 | J8: On hold — returning July 2026

Sheet Creator Applications
A1: EchoForge — Creator Applications
A2: Submission Date | B2: Full Name | C2: Primary Skill | D2: Years Experience | E2: Portfolio URL | F2: Hourly Rate ($) | G2: Availability | H2: Tier Interest | I2: Status | J2: Notes
A3: 46160 | B3: Priya Nambiar | C3: 3D Rendering | D3: 4 | E3: priyanambiar.portfolio.com | F3: 75 | G3: Available | H3: Forge Boost $79 | I3: New | J3: Strong Blender & Cinema4D portfolio, interested in ArchViz projects
A4: 46163 | B4: Eliot Faure | C4: Audio Editing | D4: 2 | E4: eliotfaure.soundcloud.com | F4: 35 | G4: Available | H4: Standard Free | I4: New | J4: Recent graduate, podcast and music production background

Sheet Deliveries Pipeline
A1: EchoForge — Deliveries Pipeline
A2: Match Date | B2: Client Name | C2: Client Contact | D2: Creator Name | E2: Creator Contact | F2: Service Type | G2: Match Type | H2: Status | I2: Forge Boost | J2: Revenue ($) | K2: Notes
A3: 46034 | B3: Mira Connelly | C3: mira.connelly@gmail.com | D3: Jordan Park | E3: jordan@jordanpark.audio | F3: Audio Editing | G3: Auto | H3: Completed | I3: No | J3: 350 | K3: Auto-matched by skill; delivered on time, 5-star review
A4: 46058 | B4: Theo Bassett | C4: theo.bassett@outlook.com | D4: Sarai Okon | E4: sarai@saraiokon.design | F4: Graphic Design | G4: Manual | H4: Completed | I4: Yes | J4: 1279 | K4: Manual match; Forge Boost applied; one revision cycle
A5: 46144 | B5: Avery Sloane | C5: avery.sloane@gmail.com | D5: Dana Voss | E5: dana@danavoss.write | F5: Content Writing | G5: Auto | H5: In Progress | I5: No | J5: 680 | K5: Rush project; 4 articles; deadline May 22

Sheet Revenue & Invoices
A1: EchoForge — Revenue & Invoices 2026
A2: Month | B2: Standard Projects (#) | C2: Standard Revenue ($) | D2: Forge Boost Projects (#) | E2: Forge Boost Revenue ($) | F2: Rush Surcharges ($) | G2: Total Monthly Revenue ($) | H2: Cumulative Revenue ($) | J2: Last Updated | K2: May 23, 2026
A3: Jan 2026 | B3: 2 | C3: =B3*250 | D3: 0 | E3: =D3*79 | F3: 0 | G3: =C3+E3+F3 | H3: =G3
A4: Feb 2026 | B4: 3 | C4: =B4*250 | D4: 0 | E4: =D4*79 | F4: 50 | G4: =C4+E4+F4 | H4: =H3+G4
A5: Mar 2026 | B5: 4 | C5: =B5*250 | D5: 1 | E5: =D5*79 | F5: 75 | G5: =C5+E5+F5 | H5: =H4+G5
A6: Apr 2026 | B6: 5 | C6: =B6*250 | D6: 1 | E6: =D6*79 | F6: 100 | G6: =C6+E6+F6 | H6: =H5+G6
A7: May 2026 | B7: 6 | C7: =B7*250 | D7: 2 | E7: =D7*79 | F7: 150 | G7: =C7+E7+F7 | H7: =H6+G7
A8: Jun 2026 | B8: 7 | C8: =B8*250 | D8: 2 | E8: =D8*79 | F8: 125 | G8: =C8+E8+F8 | H8: =H7+G8
A9: Jul 2026 | B9: 8 | C9: =B9*250 | D9: 3 | E9: =D9*79 | F9: 175 | G9: =C9+E9+F9 | H9: =H8+G9
A10: Aug 2026 | B10: 9 | C10: =B10*250 | D10: 3 | E10: =D10*79 | F10: 200 | G10: =C10+E10+F10 | H10: =H9+G10
A11: Sep 2026 | B11: 11 | C11: =B11*250 | D11: 4 | E11: =D11*79 | F11: 225 | G11: =C11+E11+F11 | H11: =H10+G11
A12: Oct 2026 | B12: 12 | C12: =B12*250 | D12: 5 | E12: =D12*79 | F12: 250 | G12: =C12+E12+F12 | H12: =H11+G12
A13: Nov 2026 | B13: 14 | C13: =B13*250 | D13: 5 | E13: =D13*79 | F13: 300 | G13: =C13+E13+F13 | H13: =H12+G13
A14: Dec 2026 | B14: 15 | C14: =B14*250 | D14: 6 | E14: =D14*79 | F14: 350 | G14: =C14+E14+F14 | H14: =H13+G14
A15: ANNUAL TOTAL | B15: =SUM(B3:B14) | C15: =SUM(C3:C14) | D15: =SUM(D3:D14) | E15: =SUM(E3:E14) | F15: =SUM(F3:F14) | G15: =SUM(G3:G14) | H15: =H14
A17: Summary & Break-Even Analysis
A18: Annual Revenue Projection ($) | B18: =G15
A19: Average Monthly Revenue ($) | B19: =G15/12
A20: Total Forge Boost Revenue ($) | B20: =E15
A21: Total Standard Revenue ($) | B21: =C15
A22: Total Rush Surcharges ($) | B22: =F15
A23: Monthly Operating Costs ($) | B23: 300
A24: Annual Operating Costs ($) | B24: =B23*12
A25: Net Annual Profit ($) | B25: =G15-B24
A26: Break-Even Month (cost $300/mo) | B26: =IFERROR(INDEX(A3:A14,MATCH(TRUE,MMULT((ROW(G3:G14)-ROW(G3)+1>=1)*1,TRANSPOSE((G3:G14>={300})*1))>=1,0)),"Not reached")

Sheet Apps Script Code
A1: EchoForge — Apps Script Reference (Read-Only)
A2: Install in Extensions > Apps Script > onFormSubmit trigger
A3: Copy the code below into your Google Apps Script editor. Attach to onFormSubmit trigger on the Creator Applications sheet.
A5: FUNCTION: matchCreator(e)
A6: Purpose: Matches new creator applications to open client projects by skill type, appends to Deliveries Pipeline, updates Assigned Creator, and emails the creator.
A8: function matchCreator(e) {
A9: // Get the active spreadsheet and relevant sheets
A10: var ss = SpreadsheetApp.getActiveSpreadsheet();
A11: var appsSheet = ss.getSheetByName('Creator Applications');
A12: var projectsSheet = ss.getSheetByName('Client Projects');
A13: var pipelineSheet = ss.getSheetByName('Deliveries Pipeline');
A15: // Read the newly submitted creator application row
... A104: 7. Check Deliveries Pipeline and Client Projects for the auto-matched row
